{
    "sourceFile": "app/Filament/Resources/InvoiceResource.php",
    "activeCommit": 0,
    "commits": [
        {
            "activePatchIndex": 46,
            "patches": [
                {
                    "date": 1716890154794,
                    "content": "Index: \n===================================================================\n--- \n+++ \n"
                },
                {
                    "date": 1716890283262,
                    "content": "Index: \n===================================================================\n--- \n+++ \n@@ -46,9 +46,8 @@\n                 Tables\\Columns\\TextColumn::make('check_out')\n                     ->date()\n                     ->sortable(),\n                 Tables\\Columns\\TextColumn::make('room_id')\n-                    ->numeric()\n                     ->sortable(),\n                 Tables\\Columns\\TextColumn::make('name_customer')\n                     ->searchable(),\n                 Tables\\Columns\\TextColumn::make('created_at')\n"
                },
                {
                    "date": 1716890327707,
                    "content": "Index: \n===================================================================\n--- \n+++ \n@@ -46,8 +46,9 @@\n                 Tables\\Columns\\TextColumn::make('check_out')\n                     ->date()\n                     ->sortable(),\n                 Tables\\Columns\\TextColumn::make('room_id')\n+                    ->relationship('room', 'No_Kamar')\n                     ->sortable(),\n                 Tables\\Columns\\TextColumn::make('name_customer')\n                     ->searchable(),\n                 Tables\\Columns\\TextColumn::make('created_at')\n"
                },
                {
                    "date": 1716890411305,
                    "content": "Index: \n===================================================================\n--- \n+++ \n@@ -47,9 +47,9 @@\n                     ->date()\n                     ->sortable(),\n                 Tables\\Columns\\TextColumn::make('room_id')\n                     ->relationship('room', 'No_Kamar')\n-                    ->sortable(),\n+                    ->required(),\n                 Tables\\Columns\\TextColumn::make('name_customer')\n                     ->searchable(),\n                 Tables\\Columns\\TextColumn::make('created_at')\n                     ->dateTime()\n"
                },
                {
                    "date": 1716890476280,
                    "content": "Index: \n===================================================================\n--- \n+++ \n@@ -27,10 +27,10 @@\n                     ->required(),\n                 Forms\\Components\\DatePicker::make('check_out')\n                     ->required(),\n                 Forms\\Components\\select::make('room_id')\n-                    ->required()\n-                    ->numeric(),\n+                    ->relationship('room', 'No_Kamar')\n+                    ->required(),\n                 Forms\\Components\\TextInput::make('name_customer')\n                     ->required()\n                     ->maxLength(255),\n             ]);\n@@ -46,9 +46,8 @@\n                 Tables\\Columns\\TextColumn::make('check_out')\n                     ->date()\n                     ->sortable(),\n                 Tables\\Columns\\TextColumn::make('room_id')\n-                    ->relationship('room', 'No_Kamar')\n                     ->required(),\n                 Tables\\Columns\\TextColumn::make('name_customer')\n                     ->searchable(),\n                 Tables\\Columns\\TextColumn::make('created_at')\n"
                },
                {
                    "date": 1716890631575,
                    "content": "Index: \n===================================================================\n--- \n+++ \n@@ -27,10 +27,10 @@\n                     ->required(),\n                 Forms\\Components\\DatePicker::make('check_out')\n                     ->required(),\n                 Forms\\Components\\select::make('room_id')\n-                    ->relationship('room', 'No_Kamar')\n-                    ->required(),\n+                    ->required()\n+                    ->numeric(),\n                 Forms\\Components\\TextInput::make('name_customer')\n                     ->required()\n                     ->maxLength(255),\n             ]);\n@@ -46,9 +46,10 @@\n                 Tables\\Columns\\TextColumn::make('check_out')\n                     ->date()\n                     ->sortable(),\n                 Tables\\Columns\\TextColumn::make('room_id')\n-                    ->required(),\n+                    ->numeric()\n+                    ->sortable(),\n                 Tables\\Columns\\TextColumn::make('name_customer')\n                     ->searchable(),\n                 Tables\\Columns\\TextColumn::make('created_at')\n                     ->dateTime()\n"
                },
                {
                    "date": 1716890669494,
                    "content": "Index: \n===================================================================\n--- \n+++ \n@@ -27,10 +27,10 @@\n                     ->required(),\n                 Forms\\Components\\DatePicker::make('check_out')\n                     ->required(),\n                 Forms\\Components\\select::make('room_id')\n-                    ->required()\n-                    ->numeric(),\n+                    ->relationship('room', 'No_Kamar')\n+                    ->required(),\n                 Forms\\Components\\TextInput::make('name_customer')\n                     ->required()\n                     ->maxLength(255),\n             ]);\n"
                },
                {
                    "date": 1716890726426,
                    "content": "Index: \n===================================================================\n--- \n+++ \n@@ -45,9 +45,9 @@\n                     ->sortable(),\n                 Tables\\Columns\\TextColumn::make('check_out')\n                     ->date()\n                     ->sortable(),\n-                Tables\\Columns\\TextColumn::make('room_id')\n+                Tables\\Columns\\TextColumn::make('room.No_Kamar')\n                     ->numeric()\n                     ->sortable(),\n                 Tables\\Columns\\TextColumn::make('name_customer')\n                     ->searchable(),\n"
                },
                {
                    "date": 1716891365383,
                    "content": "Index: \n===================================================================\n--- \n+++ \n@@ -48,8 +48,11 @@\n                     ->sortable(),\n                 Tables\\Columns\\TextColumn::make('room.No_Kamar')\n                     ->numeric()\n                     ->sortable(),\n+                Tables\\Columns\\TextColumn::make('room.Harga')\n+                    ->numeric()\n+                    ->sortable(),\n                 Tables\\Columns\\TextColumn::make('name_customer')\n                     ->searchable(),\n                 Tables\\Columns\\TextColumn::make('created_at')\n                     ->dateTime()\n"
                },
                {
                    "date": 1716891458227,
                    "content": "Index: \n===================================================================\n--- \n+++ \n@@ -49,8 +49,9 @@\n                 Tables\\Columns\\TextColumn::make('room.No_Kamar')\n                     ->numeric()\n                     ->sortable(),\n                 Tables\\Columns\\TextColumn::make('room.Harga')\n+                    ->prefix('Rp. ')\n                     ->numeric()\n                     ->sortable(),\n                 Tables\\Columns\\TextColumn::make('name_customer')\n                     ->searchable(),\n"
                },
                {
                    "date": 1716891479736,
                    "content": "Index: \n===================================================================\n--- \n+++ \n@@ -49,8 +49,9 @@\n                 Tables\\Columns\\TextColumn::make('room.No_Kamar')\n                     ->numeric()\n                     ->sortable(),\n                 Tables\\Columns\\TextColumn::make('room.Harga')\n+                    ->label('Harga')\n                     ->prefix('Rp. ')\n                     ->numeric()\n                     ->sortable(),\n                 Tables\\Columns\\TextColumn::make('name_customer')\n"
                },
                {
                    "date": 1716891844042,
                    "content": "Index: \n===================================================================\n--- \n+++ \n@@ -26,9 +26,9 @@\n                 Forms\\Components\\DatePicker::make('check_in')\n                     ->required(),\n                 Forms\\Components\\DatePicker::make('check_out')\n                     ->required(),\n-                Forms\\Components\\select::make('room_id')\n+                Forms\\Components\\Select::make('room_id')\n                     ->relationship('room', 'No_Kamar')\n                     ->required(),\n                 Forms\\Components\\TextInput::make('name_customer')\n                     ->required()\n@@ -49,14 +49,22 @@\n                 Tables\\Columns\\TextColumn::make('room.No_Kamar')\n                     ->numeric()\n                     ->sortable(),\n                 Tables\\Columns\\TextColumn::make('room.Harga')\n-                    ->label('Harga')\n+                    ->label('Harga Kamar')\n                     ->prefix('Rp. ')\n                     ->numeric()\n                     ->sortable(),\n                 Tables\\Columns\\TextColumn::make('name_customer')\n                     ->searchable(),\n+                Tables\\Columns\\TextColumn::make('total_price')\n+                    ->label('Total Harga')\n+                    ->prefix('Rp. ')\n+                    ->numeric()\n+                    ->sortable()\n+                    ->getStateUsing(function ($record) {\n+                        return $record->total_price;\n+                    }),\n                 Tables\\Columns\\TextColumn::make('created_at')\n                     ->dateTime()\n                     ->sortable()\n                     ->toggleable(isToggledHiddenByDefault: true),\n"
                },
                {
                    "date": 1716891948002,
                    "content": "Index: \n===================================================================\n--- \n+++ \n@@ -39,8 +39,10 @@\n     public static function table(Table $table): Table\n     {\n         return $table\n             ->columns([\n+                Tables\\Columns\\TextColumn::make('name_customer')\n+                    ->searchable(),\n                 Tables\\Columns\\TextColumn::make('check_in')\n                     ->date()\n                     ->sortable(),\n                 Tables\\Columns\\TextColumn::make('check_out')\n@@ -53,10 +55,9 @@\n                     ->label('Harga Kamar')\n                     ->prefix('Rp. ')\n                     ->numeric()\n                     ->sortable(),\n-                Tables\\Columns\\TextColumn::make('name_customer')\n-                    ->searchable(),\n+                \n                 Tables\\Columns\\TextColumn::make('total_price')\n                     ->label('Total Harga')\n                     ->prefix('Rp. ')\n                     ->numeric()\n"
                },
                {
                    "date": 1716892002049,
                    "content": "Index: \n===================================================================\n--- \n+++ \n@@ -55,9 +55,8 @@\n                     ->label('Harga Kamar')\n                     ->prefix('Rp. ')\n                     ->numeric()\n                     ->sortable(),\n-                \n                 Tables\\Columns\\TextColumn::make('total_price')\n                     ->label('Total Harga')\n                     ->prefix('Rp. ')\n                     ->numeric()\n"
                },
                {
                    "date": 1716892116234,
                    "content": "Index: \n===================================================================\n--- \n+++ \n@@ -1,18 +1,21 @@\n <?php\n \n namespace App\\Filament\\Resources;\n \n-use App\\Filament\\Resources\\InvoiceResource\\Pages;\n-use App\\Filament\\Resources\\InvoiceResource\\RelationManagers;\n+use Filament\\Forms;\n+use Filament\\Tables;\n use App\\Models\\Invoice;\n-use Filament\\Forms;\n use Filament\\Forms\\Form;\n+use Filament\\Tables\\Table;\n use Filament\\Resources\\Resource;\n-use Filament\\Tables;\n-use Filament\\Tables\\Table;\n+use Filament\\Forms\\Components\\Select;\n+use Filament\\Forms\\Components\\TextInput;\n+use Filament\\Forms\\Components\\DatePicker;\n use Illuminate\\Database\\Eloquent\\Builder;\n+use App\\Filament\\Resources\\InvoiceResource\\Pages;\n use Illuminate\\Database\\Eloquent\\SoftDeletingScope;\n+use App\\Filament\\Resources\\InvoiceResource\\RelationManagers;\n \n class InvoiceResource extends Resource\n {\n     protected static ?string $model = Invoice::class;\n@@ -39,8 +42,10 @@\n     public static function table(Table $table): Table\n     {\n         return $table\n             ->columns([\n+                Tables\\Columns\\RowNumberColumn::make('no_urut')\n+                ->label('Not'),\n                 Tables\\Columns\\TextColumn::make('name_customer')\n                     ->searchable(),\n                 Tables\\Columns\\TextColumn::make('check_in')\n                     ->date()\n"
                },
                {
                    "date": 1716892124550,
                    "content": "Index: \n===================================================================\n--- \n+++ \n@@ -43,9 +43,9 @@\n     {\n         return $table\n             ->columns([\n                 Tables\\Columns\\RowNumberColumn::make('no_urut')\n-                ->label('Not'),\n+                ->label('No'),\n                 Tables\\Columns\\TextColumn::make('name_customer')\n                     ->searchable(),\n                 Tables\\Columns\\TextColumn::make('check_in')\n                     ->date()\n"
                },
                {
                    "date": 1716892188898,
                    "content": "Index: \n===================================================================\n--- \n+++ \n@@ -42,10 +42,13 @@\n     public static function table(Table $table): Table\n     {\n         return $table\n             ->columns([\n-                Tables\\Columns\\RowNumberColumn::make('no_urut')\n-                ->label('No'),\n+                Tables\\Columns\\TextColumn::make('no_urut')\n+                ->label('No Urut')\n+                ->getStateUsing(function ($rowLoop, $record) {\n+                    return $rowLoop->iteration;\n+                }),\n                 Tables\\Columns\\TextColumn::make('name_customer')\n                     ->searchable(),\n                 Tables\\Columns\\TextColumn::make('check_in')\n                     ->date()\n"
                },
                {
                    "date": 1716892198617,
                    "content": "Index: \n===================================================================\n--- \n+++ \n@@ -43,12 +43,12 @@\n     {\n         return $table\n             ->columns([\n                 Tables\\Columns\\TextColumn::make('no_urut')\n-                ->label('No Urut')\n-                ->getStateUsing(function ($rowLoop, $record) {\n-                    return $rowLoop->iteration;\n-                }),\n+                    ->label('No Urut')\n+                    ->getStateUsing(function ($rowLoop, $record) {\n+                        return $rowLoop->iteration;\n+                    }),\n                 Tables\\Columns\\TextColumn::make('name_customer')\n                     ->searchable(),\n                 Tables\\Columns\\TextColumn::make('check_in')\n                     ->date()\n"
                },
                {
                    "date": 1716892213456,
                    "content": "Index: \n===================================================================\n--- \n+++ \n@@ -43,9 +43,9 @@\n     {\n         return $table\n             ->columns([\n                 Tables\\Columns\\TextColumn::make('no_urut')\n-                    ->label('No Urut')\n+                    ->label('No')\n                     ->getStateUsing(function ($rowLoop, $record) {\n                         return $rowLoop->iteration;\n                     }),\n                 Tables\\Columns\\TextColumn::make('name_customer')\n"
                },
                {
                    "date": 1716892275047,
                    "content": "Index: \n===================================================================\n--- \n+++ \n@@ -48,16 +48,18 @@\n                     ->getStateUsing(function ($rowLoop, $record) {\n                         return $rowLoop->iteration;\n                     }),\n                 Tables\\Columns\\TextColumn::make('name_customer')\n+                    ->label('Nama Pelanggan')\n                     ->searchable(),\n                 Tables\\Columns\\TextColumn::make('check_in')\n                     ->date()\n                     ->sortable(),\n                 Tables\\Columns\\TextColumn::make('check_out')\n                     ->date()\n                     ->sortable(),\n                 Tables\\Columns\\TextColumn::make('room.No_Kamar')\n+                    ->label('No Kamar')\n                     ->numeric()\n                     ->sortable(),\n                 Tables\\Columns\\TextColumn::make('room.Harga')\n                     ->label('Harga Kamar')\n"
                },
                {
                    "date": 1716905954197,
                    "content": "Index: \n===================================================================\n--- \n+++ \n@@ -87,8 +87,11 @@\n                 //\n             ])\n             ->actions([\n                 Tables\\Actions\\EditAction::make(),\n+                Action::make('PDF')\n+                    ->url(fn (Invoice $record) => route('download.pdf', $record))\n+                    ->openUrlInNewTab(),\n             ])\n             ->bulkActions([\n                 Tables\\Actions\\BulkActionGroup::make([\n                     Tables\\Actions\\DeleteBulkAction::make(),\n"
                },
                {
                    "date": 1716906016117,
                    "content": "Index: \n===================================================================\n--- \n+++ \n@@ -8,8 +8,9 @@\n use Filament\\Forms\\Form;\n use Filament\\Tables\\Table;\n use Filament\\Resources\\Resource;\n use Filament\\Forms\\Components\\Select;\n+use Filament\\Tables\\Columns\\TextColumn;\n use Filament\\Forms\\Components\\TextInput;\n use Filament\\Forms\\Components\\DatePicker;\n use Illuminate\\Database\\Eloquent\\Builder;\n use App\\Filament\\Resources\\InvoiceResource\\Pages;\n"
                },
                {
                    "date": 1716906277271,
                    "content": "Index: \n===================================================================\n--- \n+++ \n@@ -15,8 +15,9 @@\n use Illuminate\\Database\\Eloquent\\Builder;\n use App\\Filament\\Resources\\InvoiceResource\\Pages;\n use Illuminate\\Database\\Eloquent\\SoftDeletingScope;\n use App\\Filament\\Resources\\InvoiceResource\\RelationManagers;\n+use Filament\\Actions\\Action;\n \n class InvoiceResource extends Resource\n {\n     protected static ?string $model = Invoice::class;\n"
                },
                {
                    "date": 1716906321505,
                    "content": "Index: \n===================================================================\n--- \n+++ \n@@ -6,18 +6,24 @@\n use Filament\\Tables;\n use App\\Models\\Invoice;\n use Filament\\Forms\\Form;\n use Filament\\Tables\\Table;\n+use Filament\\Actions\\Action;\n use Filament\\Resources\\Resource;\n use Filament\\Forms\\Components\\Select;\n+use Filament\\Pages\\Actions\\EditAction;\n use Filament\\Tables\\Columns\\TextColumn;\n use Filament\\Forms\\Components\\TextInput;\n use Filament\\Forms\\Components\\DatePicker;\n use Illuminate\\Database\\Eloquent\\Builder;\n+use Filament\\Tables\\Actions\\BulkActionGroup;\n+use Filament\\Tables\\Actions\\DeleteBulkAction;\n use App\\Filament\\Resources\\InvoiceResource\\Pages;\n use Illuminate\\Database\\Eloquent\\SoftDeletingScope;\n use App\\Filament\\Resources\\InvoiceResource\\RelationManagers;\n-use Filament\\Actions\\Action;\n+use App\\Filament\\Resources\\InvoiceResource\\Pages\\EditInvoice;\n+use App\\Filament\\Resources\\InvoiceResource\\Pages\\ListInvoices;\n+use App\\Filament\\Resources\\InvoiceResource\\Pages\\CreateInvoice;\n \n class InvoiceResource extends Resource\n {\n     protected static ?string $model = Invoice::class;\n"
                },
                {
                    "date": 1716906348650,
                    "content": "Index: \n===================================================================\n--- \n+++ \n@@ -6,24 +6,16 @@\n use Filament\\Tables;\n use App\\Models\\Invoice;\n use Filament\\Forms\\Form;\n use Filament\\Tables\\Table;\n-use Filament\\Actions\\Action;\n use Filament\\Resources\\Resource;\n use Filament\\Forms\\Components\\Select;\n-use Filament\\Pages\\Actions\\EditAction;\n-use Filament\\Tables\\Columns\\TextColumn;\n use Filament\\Forms\\Components\\TextInput;\n use Filament\\Forms\\Components\\DatePicker;\n use Illuminate\\Database\\Eloquent\\Builder;\n-use Filament\\Tables\\Actions\\BulkActionGroup;\n-use Filament\\Tables\\Actions\\DeleteBulkAction;\n use App\\Filament\\Resources\\InvoiceResource\\Pages;\n use Illuminate\\Database\\Eloquent\\SoftDeletingScope;\n use App\\Filament\\Resources\\InvoiceResource\\RelationManagers;\n-use App\\Filament\\Resources\\InvoiceResource\\Pages\\EditInvoice;\n-use App\\Filament\\Resources\\InvoiceResource\\Pages\\ListInvoices;\n-use App\\Filament\\Resources\\InvoiceResource\\Pages\\CreateInvoice;\n \n class InvoiceResource extends Resource\n {\n     protected static ?string $model = Invoice::class;\n"
                },
                {
                    "date": 1716906561800,
                    "content": "Index: \n===================================================================\n--- \n+++ \n@@ -7,8 +7,10 @@\n use App\\Models\\Invoice;\n use Filament\\Forms\\Form;\n use Filament\\Tables\\Table;\n use Filament\\Resources\\Resource;\n+use App\\Filament\\Resources\\Action;\n+\n use Filament\\Forms\\Components\\Select;\n use Filament\\Forms\\Components\\TextInput;\n use Filament\\Forms\\Components\\DatePicker;\n use Illuminate\\Database\\Eloquent\\Builder;\n"
                },
                {
                    "date": 1716906583220,
                    "content": "Index: \n===================================================================\n--- \n+++ \n@@ -6,18 +6,23 @@\n use Filament\\Tables;\n use App\\Models\\Invoice;\n use Filament\\Forms\\Form;\n use Filament\\Tables\\Table;\n+use Filament\\Actions\\EditAction;\n use Filament\\Resources\\Resource;\n+\n use App\\Filament\\Resources\\Action;\n-\n use Filament\\Forms\\Components\\Select;\n+use Filament\\Tables\\Columns\\TextColumn;\n use Filament\\Forms\\Components\\TextInput;\n use Filament\\Forms\\Components\\DatePicker;\n use Illuminate\\Database\\Eloquent\\Builder;\n+use Filament\\Tables\\Actions\\BulkActionGroup;\n+use Filament\\Tables\\Actions\\DeleteBulkAction;\n use App\\Filament\\Resources\\InvoiceResource\\Pages;\n use Illuminate\\Database\\Eloquent\\SoftDeletingScope;\n use App\\Filament\\Resources\\InvoiceResource\\RelationManagers;\n+use App\\Filament\\Resources\\InvoiceResource\\Pages\\ListInvoices;\n \n class InvoiceResource extends Resource\n {\n     protected static ?string $model = Invoice::class;\n"
                },
                {
                    "date": 1716906851732,
                    "content": "Index: \n===================================================================\n--- \n+++ \n@@ -94,11 +94,11 @@\n                 //\n             ])\n             ->actions([\n                 Tables\\Actions\\EditAction::make(),\n-                Action::make('PDF')\n-                    ->url(fn (Invoice $record) => route('download.pdf', $record))\n-                    ->openUrlInNewTab(),\n+                // Action::make('PDF')\n+                //     ->url(fn (Invoice $record) => route('download.pdf', $record))\n+                //     ->openUrlInNewTab(),\n             ])\n             ->bulkActions([\n                 Tables\\Actions\\BulkActionGroup::make([\n                     Tables\\Actions\\DeleteBulkAction::make(),\n"
                },
                {
                    "date": 1716906911217,
                    "content": "Index: \n===================================================================\n--- \n+++ \n@@ -8,8 +8,10 @@\n use Filament\\Forms\\Form;\n use Filament\\Tables\\Table;\n use Filament\\Actions\\EditAction;\n use Filament\\Resources\\Resource;\n+use Filament\\Actions;\n+use Filament\\Pages\\Actions\\ButtonAction;\n \n use App\\Filament\\Resources\\Action;\n use Filament\\Forms\\Components\\Select;\n use Filament\\Tables\\Columns\\TextColumn;\n"
                },
                {
                    "date": 1716906917750,
                    "content": "Index: \n===================================================================\n--- \n+++ \n@@ -96,11 +96,11 @@\n                 //\n             ])\n             ->actions([\n                 Tables\\Actions\\EditAction::make(),\n-                // Action::make('PDF')\n-                //     ->url(fn (Invoice $record) => route('download.pdf', $record))\n-                //     ->openUrlInNewTab(),\n+                Action::make('PDF')\n+                    ->url(fn (Invoice $record) => route('download.pdf', $record))\n+                    ->openUrlInNewTab(),\n             ])\n             ->bulkActions([\n                 Tables\\Actions\\BulkActionGroup::make([\n                     Tables\\Actions\\DeleteBulkAction::make(),\n"
                },
                {
                    "date": 1716906981946,
                    "content": "Index: \n===================================================================\n--- \n+++ \n@@ -96,9 +96,9 @@\n                 //\n             ])\n             ->actions([\n                 Tables\\Actions\\EditAction::make(),\n-                Action::make('PDF')\n+                ButtonAction::make('PDF')\n                     ->url(fn (Invoice $record) => route('download.pdf', $record))\n                     ->openUrlInNewTab(),\n             ])\n             ->bulkActions([\n"
                },
                {
                    "date": 1716907083334,
                    "content": "Index: \n===================================================================\n--- \n+++ \n@@ -11,9 +11,8 @@\n use Filament\\Resources\\Resource;\n use Filament\\Actions;\n use Filament\\Pages\\Actions\\ButtonAction;\n \n-use App\\Filament\\Resources\\Action;\n use Filament\\Forms\\Components\\Select;\n use Filament\\Tables\\Columns\\TextColumn;\n use Filament\\Forms\\Components\\TextInput;\n use Filament\\Forms\\Components\\DatePicker;\n"
                },
                {
                    "date": 1716907113301,
                    "content": "Index: \n===================================================================\n--- \n+++ \n@@ -9,9 +9,9 @@\n use Filament\\Tables\\Table;\n use Filament\\Actions\\EditAction;\n use Filament\\Resources\\Resource;\n use Filament\\Actions;\n-use Filament\\Pages\\Actions\\ButtonAction;\n+use Filament\\Actions\\ButtonAction;\n \n use Filament\\Forms\\Components\\Select;\n use Filament\\Tables\\Columns\\TextColumn;\n use Filament\\Forms\\Components\\TextInput;\n"
                },
                {
                    "date": 1716907185935,
                    "content": "Index: \n===================================================================\n--- \n+++ \n@@ -3,14 +3,14 @@\n namespace App\\Filament\\Resources;\n \n use Filament\\Forms;\n use Filament\\Tables;\n+use Filament\\Actions;\n use App\\Models\\Invoice;\n use Filament\\Forms\\Form;\n use Filament\\Tables\\Table;\n use Filament\\Actions\\EditAction;\n use Filament\\Resources\\Resource;\n-use Filament\\Actions;\n use Filament\\Actions\\ButtonAction;\n \n use Filament\\Forms\\Components\\Select;\n use Filament\\Tables\\Columns\\TextColumn;\n@@ -22,8 +22,10 @@\n use App\\Filament\\Resources\\InvoiceResource\\Pages;\n use Illuminate\\Database\\Eloquent\\SoftDeletingScope;\n use App\\Filament\\Resources\\InvoiceResource\\RelationManagers;\n use App\\Filament\\Resources\\InvoiceResource\\Pages\\ListInvoices;\n+use App\\Filament\\Resources\\InvoiceResource\\Pages\\CreateInvoice;\n+use App\\Filament\\Resources\\InvoiceResource\\Pages\\EditInvoice;\n \n class InvoiceResource extends Resource\n {\n     protected static ?string $model = Invoice::class;\n@@ -95,9 +97,9 @@\n                 //\n             ])\n             ->actions([\n                 Tables\\Actions\\EditAction::make(),\n-                ButtonAction::make('PDF')\n+                Action::make('PDF')\n                     ->url(fn (Invoice $record) => route('download.pdf', $record))\n                     ->openUrlInNewTab(),\n             ])\n             ->bulkActions([\n"
                },
                {
                    "date": 1716907298579,
                    "content": "Index: \n===================================================================\n--- \n+++ \n@@ -3,17 +3,17 @@\n namespace App\\Filament\\Resources;\n \n use Filament\\Forms;\n use Filament\\Tables;\n-use Filament\\Actions;\n use App\\Models\\Invoice;\n use Filament\\Forms\\Form;\n use Filament\\Tables\\Table;\n use Filament\\Actions\\EditAction;\n use Filament\\Resources\\Resource;\n use Filament\\Actions\\ButtonAction;\n+use Filament\\Forms\\Components\\Select;\n \n-use Filament\\Forms\\Components\\Select;\n+use Filament\\Forms\\Components\\Actions;\n use Filament\\Tables\\Columns\\TextColumn;\n use Filament\\Forms\\Components\\TextInput;\n use Filament\\Forms\\Components\\DatePicker;\n use Illuminate\\Database\\Eloquent\\Builder;\n@@ -21,11 +21,11 @@\n use Filament\\Tables\\Actions\\DeleteBulkAction;\n use App\\Filament\\Resources\\InvoiceResource\\Pages;\n use Illuminate\\Database\\Eloquent\\SoftDeletingScope;\n use App\\Filament\\Resources\\InvoiceResource\\RelationManagers;\n+use App\\Filament\\Resources\\InvoiceResource\\Pages\\EditInvoice;\n use App\\Filament\\Resources\\InvoiceResource\\Pages\\ListInvoices;\n use App\\Filament\\Resources\\InvoiceResource\\Pages\\CreateInvoice;\n-use App\\Filament\\Resources\\InvoiceResource\\Pages\\EditInvoice;\n \n class InvoiceResource extends Resource\n {\n     protected static ?string $model = Invoice::class;\n@@ -97,9 +97,9 @@\n                 //\n             ])\n             ->actions([\n                 Tables\\Actions\\EditAction::make(),\n-                Action::make('PDF')\n+                Actions::make('PDF')\n                     ->url(fn (Invoice $record) => route('download.pdf', $record))\n                     ->openUrlInNewTab(),\n             ])\n             ->bulkActions([\n"
                },
                {
                    "date": 1716907321232,
                    "content": "Index: \n===================================================================\n--- \n+++ \n@@ -3,17 +3,17 @@\n namespace App\\Filament\\Resources;\n \n use Filament\\Forms;\n use Filament\\Tables;\n+use Filament\\Actions;\n use App\\Models\\Invoice;\n use Filament\\Forms\\Form;\n use Filament\\Tables\\Table;\n use Filament\\Actions\\EditAction;\n use Filament\\Resources\\Resource;\n use Filament\\Actions\\ButtonAction;\n+\n use Filament\\Forms\\Components\\Select;\n-\n-use Filament\\Forms\\Components\\Actions;\n use Filament\\Tables\\Columns\\TextColumn;\n use Filament\\Forms\\Components\\TextInput;\n use Filament\\Forms\\Components\\DatePicker;\n use Illuminate\\Database\\Eloquent\\Builder;\n@@ -21,11 +21,11 @@\n use Filament\\Tables\\Actions\\DeleteBulkAction;\n use App\\Filament\\Resources\\InvoiceResource\\Pages;\n use Illuminate\\Database\\Eloquent\\SoftDeletingScope;\n use App\\Filament\\Resources\\InvoiceResource\\RelationManagers;\n-use App\\Filament\\Resources\\InvoiceResource\\Pages\\EditInvoice;\n use App\\Filament\\Resources\\InvoiceResource\\Pages\\ListInvoices;\n use App\\Filament\\Resources\\InvoiceResource\\Pages\\CreateInvoice;\n+use App\\Filament\\Resources\\InvoiceResource\\Pages\\EditInvoice;\n \n class InvoiceResource extends Resource\n {\n     protected static ?string $model = Invoice::class;\n"
                },
                {
                    "date": 1716907388213,
                    "content": "Index: \n===================================================================\n--- \n+++ \n@@ -10,9 +10,9 @@\n use Filament\\Tables\\Table;\n use Filament\\Actions\\EditAction;\n use Filament\\Resources\\Resource;\n use Filament\\Actions\\ButtonAction;\n-\n+use Filament\\Actions\\Actions;\n use Filament\\Forms\\Components\\Select;\n use Filament\\Tables\\Columns\\TextColumn;\n use Filament\\Forms\\Components\\TextInput;\n use Filament\\Forms\\Components\\DatePicker;\n"
                },
                {
                    "date": 1716907451291,
                    "content": "Index: \n===================================================================\n--- \n+++ \n@@ -10,9 +10,10 @@\n use Filament\\Tables\\Table;\n use Filament\\Actions\\EditAction;\n use Filament\\Resources\\Resource;\n use Filament\\Actions\\ButtonAction;\n-use Filament\\Actions\\Actions;\n+use Filament\\Actions\\Action;\n+\n use Filament\\Forms\\Components\\Select;\n use Filament\\Tables\\Columns\\TextColumn;\n use Filament\\Forms\\Components\\TextInput;\n use Filament\\Forms\\Components\\DatePicker;\n"
                },
                {
                    "date": 1716907469423,
                    "content": "Index: \n===================================================================\n--- \n+++ \n@@ -98,12 +98,13 @@\n                 //\n             ])\n             ->actions([\n                 Tables\\Actions\\EditAction::make(),\n-                Actions::make('PDF')\n+                Action::make('PDF')\n                     ->url(fn (Invoice $record) => route('download.pdf', $record))\n                     ->openUrlInNewTab(),\n             ])\n+            \n             ->bulkActions([\n                 Tables\\Actions\\BulkActionGroup::make([\n                     Tables\\Actions\\DeleteBulkAction::make(),\n                 ]),\n"
                },
                {
                    "date": 1716907475880,
                    "content": "Index: \n===================================================================\n--- \n+++ \n@@ -101,10 +101,9 @@\n                 Tables\\Actions\\EditAction::make(),\n                 Action::make('PDF')\n                     ->url(fn (Invoice $record) => route('download.pdf', $record))\n                     ->openUrlInNewTab(),\n-            ])\n-            \n+            ])            \n             ->bulkActions([\n                 Tables\\Actions\\BulkActionGroup::make([\n                     Tables\\Actions\\DeleteBulkAction::make(),\n                 ]),\n"
                },
                {
                    "date": 1716907931490,
                    "content": "Index: \n===================================================================\n--- \n+++ \n@@ -3,17 +3,13 @@\n namespace App\\Filament\\Resources;\n \n use Filament\\Forms;\n use Filament\\Tables;\n-use Filament\\Actions;\n use App\\Models\\Invoice;\n use Filament\\Forms\\Form;\n use Filament\\Tables\\Table;\n use Filament\\Actions\\EditAction;\n use Filament\\Resources\\Resource;\n-use Filament\\Actions\\ButtonAction;\n-use Filament\\Actions\\Action;\n-\n use Filament\\Forms\\Components\\Select;\n use Filament\\Tables\\Columns\\TextColumn;\n use Filament\\Forms\\Components\\TextInput;\n use Filament\\Forms\\Components\\DatePicker;\n"
                },
                {
                    "date": 1716907942345,
                    "content": "Index: \n===================================================================\n--- \n+++ \n@@ -94,11 +94,11 @@\n                 //\n             ])\n             ->actions([\n                 Tables\\Actions\\EditAction::make(),\n-                Action::make('PDF')\n-                    ->url(fn (Invoice $record) => route('download.pdf', $record))\n-                    ->openUrlInNewTab(),\n+                // Action::make('PDF')\n+                //     ->url(fn (Invoice $record) => route('download.pdf', $record))\n+                //     ->openUrlInNewTab(),\n             ])            \n             ->bulkActions([\n                 Tables\\Actions\\BulkActionGroup::make([\n                     Tables\\Actions\\DeleteBulkAction::make(),\n"
                },
                {
                    "date": 1716907954848,
                    "content": "Index: \n===================================================================\n--- \n+++ \n@@ -94,11 +94,11 @@\n                 //\n             ])\n             ->actions([\n                 Tables\\Actions\\EditAction::make(),\n-                // Action::make('PDF')\n-                //     ->url(fn (Invoice $record) => route('download.pdf', $record))\n-                //     ->openUrlInNewTab(),\n+                Action::make('PDF')\n+                    ->url(fn (Invoice $record) => route('download.pdf', $record))\n+                    ->openUrlInNewTab(),\n             ])            \n             ->bulkActions([\n                 Tables\\Actions\\BulkActionGroup::make([\n                     Tables\\Actions\\DeleteBulkAction::make(),\n"
                },
                {
                    "date": 1716907969885,
                    "content": "Index: \n===================================================================\n--- \n+++ \n@@ -8,8 +8,9 @@\n use Filament\\Forms\\Form;\n use Filament\\Tables\\Table;\n use Filament\\Actions\\EditAction;\n use Filament\\Resources\\Resource;\n+use Filament\\Tables\\Actions\\Action;\n use Filament\\Forms\\Components\\Select;\n use Filament\\Tables\\Columns\\TextColumn;\n use Filament\\Forms\\Components\\TextInput;\n use Filament\\Forms\\Components\\DatePicker;\n@@ -18,11 +19,11 @@\n use Filament\\Tables\\Actions\\DeleteBulkAction;\n use App\\Filament\\Resources\\InvoiceResource\\Pages;\n use Illuminate\\Database\\Eloquent\\SoftDeletingScope;\n use App\\Filament\\Resources\\InvoiceResource\\RelationManagers;\n+use App\\Filament\\Resources\\InvoiceResource\\Pages\\EditInvoice;\n use App\\Filament\\Resources\\InvoiceResource\\Pages\\ListInvoices;\n use App\\Filament\\Resources\\InvoiceResource\\Pages\\CreateInvoice;\n-use App\\Filament\\Resources\\InvoiceResource\\Pages\\EditInvoice;\n \n class InvoiceResource extends Resource\n {\n     protected static ?string $model = Invoice::class;\n"
                },
                {
                    "date": 1716908003425,
                    "content": "Index: \n===================================================================\n--- \n+++ \n@@ -95,9 +95,9 @@\n                 //\n             ])\n             ->actions([\n                 Tables\\Actions\\EditAction::make(),\n-                Action::make('PDF')\n+                Action::make('cetak')\n                     ->url(fn (Invoice $record) => route('download.pdf', $record))\n                     ->openUrlInNewTab(),\n             ])            \n             ->bulkActions([\n"
                },
                {
                    "date": 1716913590356,
                    "content": "Index: \n===================================================================\n--- \n+++ \n@@ -55,8 +55,11 @@\n                     ->label('No')\n                     ->getStateUsing(function ($rowLoop, $record) {\n                         return $rowLoop->iteration;\n                     }),\n+                Tables\\Columns\\TextColumn::make('room.invoice_number')\n+                    ->label('No Invoice')\n+                    ->searchable(),\n                 Tables\\Columns\\TextColumn::make('name_customer')\n                     ->label('Nama Pelanggan')\n                     ->searchable(),\n                 Tables\\Columns\\TextColumn::make('check_in')\n"
                },
                {
                    "date": 1716913671332,
                    "content": "Index: \n===================================================================\n--- \n+++ \n@@ -55,9 +55,9 @@\n                     ->label('No')\n                     ->getStateUsing(function ($rowLoop, $record) {\n                         return $rowLoop->iteration;\n                     }),\n-                Tables\\Columns\\TextColumn::make('room.invoice_number')\n+                Tables\\Columns\\TextColumn::make('invoice_number')\n                     ->label('No Invoice')\n                     ->searchable(),\n                 Tables\\Columns\\TextColumn::make('name_customer')\n                     ->label('Nama Pelanggan')\n"
                }
            ],
            "date": 1716890154794,
            "name": "Commit-0",
            "content": "<?php\n\nnamespace App\\Filament\\Resources;\n\nuse App\\Filament\\Resources\\InvoiceResource\\Pages;\nuse App\\Filament\\Resources\\InvoiceResource\\RelationManagers;\nuse App\\Models\\Invoice;\nuse Filament\\Forms;\nuse Filament\\Forms\\Form;\nuse Filament\\Resources\\Resource;\nuse Filament\\Tables;\nuse Filament\\Tables\\Table;\nuse Illuminate\\Database\\Eloquent\\Builder;\nuse Illuminate\\Database\\Eloquent\\SoftDeletingScope;\n\nclass InvoiceResource extends Resource\n{\n    protected static ?string $model = Invoice::class;\n\n    protected static ?string $navigationIcon = 'heroicon-o-rectangle-stack';\n\n    public static function form(Form $form): Form\n    {\n        return $form\n            ->schema([\n                Forms\\Components\\DatePicker::make('check_in')\n                    ->required(),\n                Forms\\Components\\DatePicker::make('check_out')\n                    ->required(),\n                Forms\\Components\\select::make('room_id')\n                    ->required()\n                    ->numeric(),\n                Forms\\Components\\TextInput::make('name_customer')\n                    ->required()\n                    ->maxLength(255),\n            ]);\n    }\n\n    public static function table(Table $table): Table\n    {\n        return $table\n            ->columns([\n                Tables\\Columns\\TextColumn::make('check_in')\n                    ->date()\n                    ->sortable(),\n                Tables\\Columns\\TextColumn::make('check_out')\n                    ->date()\n                    ->sortable(),\n                Tables\\Columns\\TextColumn::make('room_id')\n                    ->numeric()\n                    ->sortable(),\n                Tables\\Columns\\TextColumn::make('name_customer')\n                    ->searchable(),\n                Tables\\Columns\\TextColumn::make('created_at')\n                    ->dateTime()\n                    ->sortable()\n                    ->toggleable(isToggledHiddenByDefault: true),\n                Tables\\Columns\\TextColumn::make('updated_at')\n                    ->dateTime()\n                    ->sortable()\n                    ->toggleable(isToggledHiddenByDefault: true),\n            ])\n            ->filters([\n                //\n            ])\n            ->actions([\n                Tables\\Actions\\EditAction::make(),\n            ])\n            ->bulkActions([\n                Tables\\Actions\\BulkActionGroup::make([\n                    Tables\\Actions\\DeleteBulkAction::make(),\n                ]),\n            ]);\n    }\n\n    public static function getRelations(): array\n    {\n        return [\n            //\n        ];\n    }\n\n    public static function getPages(): array\n    {\n        return [\n            'index' => Pages\\ListInvoices::route('/'),\n            'create' => Pages\\CreateInvoice::route('/create'),\n            'edit' => Pages\\EditInvoice::route('/{record}/edit'),\n        ];\n    }\n}"
        }
    ]
}